psmon/__init__.py
psmon/base.py
psmon/limiters/__init__.py
psmon/limiters/base.py
psmon/limiters/cpu_times.py
psmon/limiters/max_memory.py
psmon/limiters/wall_time.py
psmon/main.py
psmon/utils.py
psmon-1.1.1.dist-info/LICENSE
psmon-1.1.1.dist-info/WHEEL
psmon-1.1.1.dist-info/METADATA
psmon-1.1.1.dist-info/RECORD
